{
  "products": [
    {
      "id": 1,
      "name": "Magic Peacock",
      "description": "Magnificent peacock-inspired fireworks with cascading colors that mesmerize crowds. A stunning display of nature's beauty captured in brilliant lights.",
      "image": "/images/little-peacock.jpg",
      "tag": "TRENDING",
      "tagStyle": "trending",
      "price": "₹599",
      "category": "Fancy Items",
      "effectType": "Mixed",
      "noiseLevel": "Medium",
      "featured": true
    },
    {
      "id": 2,
      "name": "Mystic Wonder Pack",
      "description": "A comprehensive collection of assorted fireworks for every occasion. Perfect for family celebrations with soft sparks and peaceful vibes.",
      "image": "/images/coming soon.png",
      "tag": "",
      "tagStyle": "",
      "price": "₹799",
      "category": "Fancy Items",
      "effectType": "Mixed",
      "noiseLevel": "Low",
      "featured": true
    },
    {
      "id": 3,
      "name": "Coming Soon",
      "description": "Will be Revealed Soon. An exciting new collection is in the works. Stay tuned for our latest fireworks innovation.",
      "image": "/images/coming soon.png",
      "tag": "SURPRISE",
      "tagStyle": "surprise",
      "price": "N/A",
      "category": "Coming Soon",
      "effectType": "Mixed",
      "noiseLevel": "TBD",
      "comingSoon": true
    },
    {
      "id": 4,
      "name": "Featured Collection",
      "description": "Will be Launched Soon. A special featured collection designed for premium celebrations. Exceptional quality and stunning visual effects.",
      "image": "/images/coming soon.png",
      "tag": "FEATURE",
      "tagStyle": "feature",
      "price": "N/A",
      "category": "Featured",
      "effectType": "Mixed",
      "noiseLevel": "TBD",
      "comingSoon": true
    }
  ],
  "categories": [
    "All Categories",
    "Sparklers",
    "Rockets",
    "Flower Pots",
    "Fountains",
    "Fancy Items",
    "Ground Chakkars",
    "Kids Friendly"
  ],
  "filters": {
    "effectType": ["Ground", "Mixed"],
    "noiseLevel": ["Low", "Medium", "High"]
  }
}
